taswira/__init__.py
taswira/__main__.py
taswira/app.py
taswira/units.py
taswira/scripts/__init__.py
taswira/scripts/arg_types.py
taswira/scripts/console.py
taswira/scripts/helpers.py
taswira/scripts/ingestion.py
taswira/scripts/metadata.py
taswira-0.1.3.dist-info/licenses/LICENSE
taswira-0.1.3.dist-info/METADATA
taswira-0.1.3.dist-info/WHEEL
taswira-0.1.3.dist-info/entry_points.txt
taswira-0.1.3.dist-info/top_level.txt
taswira-0.1.3.dist-info/RECORD
