Metadata-Version: 2.4
Name: taswira
Version: 0.1.3
Summary: An interactive visualization tool for GCBM
Home-page: https://github.com/moja-global/taswira
Author: moja global
License: MPL2
Classifier: Development Status :: 3 - Alpha
Classifier: Intended Audience :: Other Audience
Classifier: Topic :: Scientific/Engineering :: GIS
Classifier: License :: OSI Approved :: Mozilla Public License 2.0 (MPL 2.0)
Classifier: Programming Language :: Python :: 3
Classifier: Programming Language :: Python :: 3.6
Classifier: Programming Language :: Python :: 3 :: Only
Requires-Python: >=3.6
License-File: LICENSE
Requires-Dist: terracotta==0.6.0
Requires-Dist: dash==1.13.3
Requires-Dist: dash-leaflet==0.0.19
Requires-Dist: plotly==4.8.2
Requires-Dist: Werkzeug==1.0.1
Requires-Dist: tqdm==4.47.0
Requires-Dist: MarkupSafe==2.0.1
Dynamic: author
Dynamic: classifier
Dynamic: description
Dynamic: description-content-type
Dynamic: home-page
Dynamic: license
Dynamic: license-file
Dynamic: requires-dist
Dynamic: requires-python
Dynamic: summary
